{
  "data": [
    {
      "email": "ryangustin16@hotmail.com",
      "pass": "X8?J8kzdPs?Qn&Fg3e&4",
      "level": 1,
      "point": "3638",
      "lastRun": "2023-08-13T10:48:33+07:00"
    },
    {
      "email": "benbouishtif@hotmail.com",
      "pass": "DTZHpTOl74",
      "level": 1,
      "point": "345",
      "lastRun": "2023-08-14T10:48:33+07:00"
    },
    {
      "email": "ozberkedwihe@hotmail.com",
      "pass": "LcDEo88n53",
      "level": 1,
      "point": "318",
      "lastRun": "2023-08-14T10:52:13+07:00"
    },
    {
      "email": "unrathhamizic@outlook.com",
      "pass": "I2RB6F48",
      "level": 1,
      "point": "295",
      "lastRun": "2023-08-14T11:00:26+07:00"
    },
    {
      "email": "ickaylijayav@outlook.com",
      "pass": "RnOEq074",
      "level": 1,
      "point": "315",
      "lastRun": "2023-08-14T11:03:48+07:00"
    },
    {
      "email": "furtulipatj@outlook.com",
      "pass": "v2eaau43",
      "level": 1,
      "point": "345",
      "lastRun": "2023-08-14T11:07:19+07:00"
    },
    {
      "email": "dadonnoliany@outlook.com",
      "pass": "qHAvMM11",
      "level": 1,
      "point": "295",
      "lastRun": "2023-08-14T11:10:57+07:00"
    },
    {
      "email": "kwaalilgy3@hotmail.com",
      "pass": "qPOC6n3v45",
      "level": 1,
      "point": "295",
      "lastRun": "2023-08-14T11:14:59+07:00"
    },
    {
      "email": "suszyouarab@hotmail.com",
      "pass": "1kuctmdS96",
      "level": 1,
      "point": "345",
      "lastRun": "2023-08-14T11:17:24+07:00"
    },
    {
      "email": "sebishmakrmeh@hotmail.com",
      "pass": "mQMH8GXe74",
      "level": 1,
      "point": "345",
      "lastRun": "2023-08-14T11:22:17+07:00"
    },
    {
      "email": "omakclon7@hotmail.com",
      "pass": "aBmFUS6s20",
      "level": 1,
      "point": "229",
      "lastRun": "2023-08-14T11:25:02+07:00"
    },
    {
      "email": "xosrooppie6@hotmail.com",
      "pass": "hRpRi0PL84",
      "level": 1,
      "point": "229",
      "lastRun": "2023-08-14T11:28:32+07:00"
    },
    {
      "email": "rawksinamox@hotmail.com",
      "pass": "lALIdDZx37",
      "level": 1,
      "point": "279",
      "lastRun": "2023-08-14T11:31:58+07:00"
    },
    {
      "email": "getevmaajar@hotmail.com",
      "pass": "IcUvQEbL15",
      "level": 1,
      "point": "229",
      "lastRun": "2023-08-14T11:37:10+07:00"
    },
    {
      "email": "bakijeyxcoyp@hotmail.com",
      "pass": "vZ8tvGus18",
      "level": 1,
      "point": "229",
      "lastRun": "2023-08-14T11:56:41+07:00"
    },
    {
      "email": "zaterottativ@hotmail.com",
      "pass": "CnrkY7d458",
      "level": 1,
      "point": "229",
      "lastRun": "2023-08-14T11:59:36+07:00"
    },
    {
      "email": "nkennevalori8@outlook.com",
      "pass": "dzZYQ857",
      "level": 1,
      "point": "239",
      "lastRun": "2023-08-14T12:03:01+07:00"
    },
    {
      "email": "ciabasimiy@outlook.com",
      "pass": "U5E4by76",
      "level": 1,
      "point": "279",
      "lastRun": "2023-08-14T12:06:53+07:00"
    },
    {
      "email": "ojomofieglc@outlook.com",
      "pass": "stGUgy00",
      "level": 1,
      "point": "229",
      "lastRun": "2023-08-14T12:09:48+07:00"
    },
    {
      "email": "gasmettougaa@outlook.com",
      "pass": "NUmCH119",
      "level": 1,
      "point": "294",
      "lastRun": "2023-08-14T12:12:18+07:00"
    }
  ]
}
